MANIFEST.in
README.rst
setup.py
android_flasher.egg-info/PKG-INFO
android_flasher.egg-info/SOURCES.txt
android_flasher.egg-info/dependency_links.txt
android_flasher.egg-info/entry_points.txt
android_flasher.egg-info/requires.txt
android_flasher.egg-info/top_level.txt
flasher/__init__.py
flasher/cli.py
flasher/flasher.py