Metadata-Version: 1.0
Name: android-flasher
Version: 1.2
Summary: Flash the Android factory image without removing your data.
Home-page: https://github.com/minsoopark/android-flasher
Author: Minsoo Park
Author-email: minsoo1003@gmail.com
License: MIT License
Keywords: flasher,android-flasher
Platform: UNKNOWN
